{"id": "nat11813", "name": "Sligo Golf Course", "loc": [39.01414, -77.0278], "state": "Maryland", "teeSets": [{"id": "nwhiteblu", "name": "White/Blue", "rating": 62.4, "slope": 102, "yds": [254, 135, 285, 160, 252, 260, 278, 252, 394, 261, 160, 296, 195, 260, 272, 298, 260, 414]}, {"id": "nforward", "name": "Forward", "rating": 60, "slope": 96, "yds": [245, 122, 220, 150, 210, 262, 325, 251, 245, 245, 122, 220, 150, 210, 262, 325, 251, 245]}, {"id": "nwhitebluw", "name": "White/Blue (W)", "rating": 66.8, "slope": 112, "yds": [254, 135, 285, 160, 252, 260, 278, 252, 394, 261, 160, 296, 195, 260, 272, 298, 260, 414]}, {"id": "nforwardw", "name": "Forward (W)", "rating": 63.8, "slope": 107, "yds": [245, 122, 220, 150, 210, 262, 325, 251, 245, 245, 122, 220, 150, 210, 262, 325, 251, 245]}], "holes": [{"par": 4, "si": 16}, {"par": 3, "si": 18}, {"par": 4, "si": 8}, {"par": 3, "si": 6}, {"par": 4, "si": 14}, {"par": 4, "si": 10}, {"par": 4, "si": 4}, {"par": 4, "si": 12}, {"par": 4, "si": 2}], "tier": "gps", "geoUrl": "geo/nat/maryland/11813.json", "nVerified": 7, "solved": false}