{"id": "nat11907", "name": "Heathers Club of Bloomfield", "loc": [42.6073, -83.23287], "state": "Michigan", "teeSets": [{"id": "nblack", "name": "BLACK", "rating": 71.4, "slope": 136, "yds": [388, 573, 230, 345, 337, 210, 343, 321, 380, 388, 573, 230, 345, 337, 210, 343, 321, 380]}, {"id": "nblueblac", "name": "BLUE/BLACK", "rating": 70.4, "slope": 133, "yds": [382, 498, 183, 322, 300, 196, 334, 313, 317, 388, 573, 230, 345, 337, 210, 343, 321, 380]}, {"id": "nblue", "name": "BLUE", "rating": 69.4, "slope": 129, "yds": [382, 498, 183, 322, 300, 196, 334, 313, 317, 382, 498, 183, 322, 300, 196, 334, 313, 317]}, {"id": "nwhiteblu", "name": "WHITE/BLUE", "rating": 68.5, "slope": 128, "yds": [350, 473, 136, 278, 281, 172, 325, 303, 308, 382, 498, 183, 322, 300, 196, 334, 313, 317]}, {"id": "nwhite", "name": "WHITE", "rating": 67.6, "slope": 126, "yds": [350, 473, 136, 278, 281, 172, 325, 303, 308, 350, 473, 136, 278, 281, 172, 325, 303, 308]}, {"id": "ngoldwhit", "name": "GOLD/WHITE", "rating": 67, "slope": 125, "yds": [350, 455, 136, 261, 270, 154, 294, 274, 308, 350, 473, 136, 278, 281, 172, 325, 303, 308]}, {"id": "ngold", "name": "GOLD", "rating": 66.4, "slope": 124, "yds": [350, 455, 136, 261, 270, 154, 294, 274, 308, 350, 455, 136, 261, 270, 154, 294, 274, 308]}, {"id": "nred", "name": "RED", "rating": 63.8, "slope": 119, "yds": [339, 442, 118, 241, 255, 119, 284, 168, 272, 339, 442, 118, 241, 255, 119, 284, 168, 272]}, {"id": "nbluew", "name": "BLUE (W)", "rating": 74.2, "slope": 137, "yds": [382, 498, 183, 322, 300, 196, 334, 313, 317, 382, 498, 183, 322, 300, 196, 334, 313, 317]}, {"id": "nwhitew", "name": "WHITE (W)", "rating": 72.6, "slope": 130, "yds": [350, 473, 136, 278, 281, 172, 325, 303, 308, 350, 473, 136, 278, 281, 172, 325, 303, 308]}], "holes": [{"par": 4, "si": 8}, {"par": 5, "si": 10}, {"par": 3, "si": 18}, {"par": 4, "si": 6}, {"par": 4, "si": 12}, {"par": 3, "si": 16}, {"par": 4, "si": 2}, {"par": 4, "si": 4}, {"par": 4, "si": 14}], "tier": "gps", "geoUrl": "geo/nat/mi/11907.json", "nVerified": 8, "solved": false}