{"id": "nat11180", "name": "Bayonet at Puppy Creek", "loc": [35.01451, -79.12761], "state": "North Carolina", "teeSets": [{"id": "nblacktee", "name": "Black Tees", "rating": 73.9, "slope": 148, "yds": [506, 421, 169, 411, 520, 416, 393, 450, 175, 349, 389, 396, 397, 187, 466, 191, 456, 527]}, {"id": "nbluetees", "name": "Blue Tees", "rating": 71.2, "slope": 138, "yds": [471, 398, 153, 386, 493, 356, 365, 419, 163, 316, 348, 354, 357, 166, 449, 161, 431, 495]}, {"id": "nwhitetee", "name": "White Tees", "rating": 69.2, "slope": 127, "yds": [433, 370, 134, 366, 440, 326, 345, 378, 142, 292, 308, 317, 346, 140, 415, 148, 402, 450]}, {"id": "ngoldtees", "name": "Gold Tees", "rating": 66.2, "slope": 118, "yds": [388, 330, 121, 296, 402, 298, 309, 317, 131, 272, 277, 282, 314, 133, 378, 132, 329, 413]}, {"id": "nredtees", "name": "Red Tees", "rating": 62.8, "slope": 114, "yds": [307, 284, 113, 240, 363, 218, 285, 267, 69, 264, 213, 246, 254, 116, 339, 94, 241, 338]}, {"id": "nwhiteteew", "name": "White Tees (W)", "rating": 74.3, "slope": 141, "yds": [433, 370, 134, 366, 440, 326, 345, 378, 142, 292, 308, 317, 346, 140, 415, 148, 402, 450]}, {"id": "ngoldteesw", "name": "Gold Tees (W)", "rating": 70.8, "slope": 130, "yds": [388, 330, 121, 296, 402, 298, 309, 317, 131, 272, 277, 282, 314, 133, 378, 132, 329, 413]}, {"id": "nredteesw", "name": "Red Tees (W)", "rating": 65.5, "slope": 115, "yds": [307, 284, 113, 240, 363, 218, 285, 267, 69, 264, 213, 246, 254, 116, 339, 94, 241, 338]}], "holes": [{"par": 5, "si": 7}, {"par": 4, "si": 1}, {"par": 3, "si": 15}, {"par": 4, "si": 3}, {"par": 5, "si": 13}, {"par": 4, "si": 9}, {"par": 4, "si": 11}, {"par": 4, "si": 5}, {"par": 3, "si": 17}, {"par": 4, "si": 14}, {"par": 4, "si": 8}, {"par": 4, "si": 16}, {"par": 4, "si": 4}, {"par": 3, "si": 6}, {"par": 5, "si": 12}, {"par": 3, "si": 10}, {"par": 4, "si": 2}, {"par": 5, "si": 18}], "tier": "gps", "geoUrl": "geo/nat/northcarolin/11180.json", "nVerified": 15, "solved": false}