{"id": "nat1303", "name": "The Golf Club at Windham", "loc": [41.72522, -72.18561], "state": "Connecticut", "teeSets": [{"id": "nblack", "name": "Black", "rating": 69.4, "slope": 118, "yds": [394, 289, 149, 255, 481, 182, 348, 392, 115, 467, 546, 459, 367, 251, 506, 168, 428, 232]}, {"id": "nwhite", "name": "White", "rating": 67.6, "slope": 115, "yds": [370, 275, 139, 237, 462, 169, 324, 360, 107, 440, 508, 435, 323, 233, 475, 156, 420, 208]}, {"id": "nyellow", "name": "Yellow", "rating": 65, "slope": 108, "yds": [304, 265, 128, 222, 414, 156, 299, 320, 99, 425, 470, 395, 298, 216, 447, 147, 335, 143]}, {"id": "nred", "name": "Red", "rating": 63.5, "slope": 104, "yds": [294, 246, 120, 197, 409, 148, 286, 310, 68, 410, 434, 332, 249, 204, 441, 141, 328, 133]}, {"id": "nblackw", "name": "Black (W)", "rating": 74.4, "slope": 123, "yds": [394, 289, 149, 255, 481, 182, 348, 392, 115, 467, 546, 459, 367, 251, 506, 168, 428, 232]}, {"id": "nwhitew", "name": "White (W)", "rating": 72.3, "slope": 119, "yds": [370, 275, 139, 237, 462, 169, 324, 360, 107, 440, 508, 435, 323, 233, 475, 156, 420, 208]}, {"id": "nyelloww", "name": "Yellow (W)", "rating": 69.1, "slope": 116, "yds": [304, 265, 128, 222, 414, 156, 299, 320, 99, 425, 470, 395, 298, 216, 447, 147, 335, 143]}, {"id": "nredw", "name": "Red (W)", "rating": 67.3, "slope": 109, "yds": [294, 246, 120, 197, 409, 148, 286, 310, 68, 410, 434, 332, 249, 204, 441, 141, 328, 133]}], "holes": [{"par": 4, "si": 6}, {"par": 4, "si": 14}, {"par": 3, "si": 10}, {"par": 4, "si": 16}, {"par": 5, "si": 12}, {"par": 3, "si": 4}, {"par": 4, "si": 8}, {"par": 4, "si": 2}, {"par": 3, "si": 18}, {"par": 5, "si": 15}, {"par": 5, "si": 5}, {"par": 4, "si": 1}, {"par": 4, "si": 11}, {"par": 4, "si": 17}, {"par": 5, "si": 13}, {"par": 3, "si": 9}, {"par": 4, "si": 7}, {"par": 3, "si": 3}], "tier": "gps", "geoUrl": "geo/nat/connecticut/1303.json", "nVerified": 11, "solved": false}