{"id": "nat199", "name": "Eagle Ridge Golf Club", "loc": [26.53016, -81.83248], "state": "Florida", "teeSets": [{"id": "nblue", "name": "BLUE", "rating": 71.4, "slope": 122, "yds": [346, 419, 486, 383, 186, 376, 513, 169, 406, 347, 460, 362, 548, 197, 287, 197, 434, 354]}, {"id": "nwhite", "name": "WHITE", "rating": 69.2, "slope": 116, "yds": [338, 386, 452, 356, 171, 326, 497, 154, 353, 321, 451, 344, 497, 150, 268, 167, 401, 333]}, {"id": "nwhitegol", "name": "WHITE/GOLD", "rating": 68.2, "slope": 115, "yds": [338, 352, 452, 356, 118, 326, 461, 154, 353, 321, 451, 344, 444, 150, 268, 167, 347, 333]}, {"id": "ngold", "name": "GOLD", "rating": 66.6, "slope": 112, "yds": [306, 352, 442, 343, 118, 313, 461, 131, 319, 295, 412, 329, 444, 123, 252, 148, 347, 312]}, {"id": "nred", "name": "RED", "rating": 63.9, "slope": 107, "yds": [289, 310, 402, 298, 91, 279, 429, 114, 271, 282, 378, 314, 422, 98, 215, 126, 299, 259]}, {"id": "ngoldw", "name": "GOLD (W)", "rating": 71.5, "slope": 120, "yds": [306, 352, 442, 343, 118, 313, 461, 131, 319, 295, 412, 329, 444, 123, 252, 148, 347, 312]}, {"id": "nredw", "name": "RED (W)", "rating": 68.3, "slope": 114, "yds": [289, 310, 402, 298, 91, 279, 429, 114, 271, 282, 378, 314, 422, 98, 215, 126, 299, 259]}], "holes": [{"par": 4, "si": 15}, {"par": 4, "si": 1}, {"par": 5, "si": 7}, {"par": 4, "si": 11}, {"par": 3, "si": 5}, {"par": 4, "si": 3}, {"par": 5, "si": 9}, {"par": 3, "si": 17}, {"par": 4, "si": 13}, {"par": 4, "si": 6}, {"par": 5, "si": 8}, {"par": 4, "si": 10}, {"par": 5, "si": 4}, {"par": 3, "si": 18}, {"par": 4, "si": 16}, {"par": 3, "si": 14}, {"par": 4, "si": 2}, {"par": 4, "si": 12}], "tier": "gps", "geoUrl": "geo/nat/fl/199.json", "nVerified": 18, "solved": false}