{"id": "nat10465", "name": "Copper Creek Golf Course", "loc": [41.60878, -93.51574], "state": "Iowa", "teeSets": [{"id": "nblue", "name": "Blue", "rating": 70.2, "slope": 119, "yds": [490, 175, 564, 422, 176, 372, 441, 184, 422, 512, 355, 192, 344, 524, 139, 352, 317, 297]}, {"id": "nwhite", "name": "White", "rating": 68.1, "slope": 118, "yds": [478, 163, 530, 394, 168, 348, 396, 171, 358, 478, 327, 154, 326, 517, 130, 349, 303, 284]}, {"id": "nyellow", "name": "Yellow", "rating": 65.5, "slope": 111, "yds": [405, 152, 498, 344, 146, 328, 353, 140, 344, 394, 310, 148, 285, 437, 115, 340, 298, 267]}, {"id": "nred", "name": "Red", "rating": 63.3, "slope": 100, "yds": [400, 105, 460, 298, 106, 316, 318, 125, 296, 390, 293, 140, 280, 427, 109, 246, 259, 204]}, {"id": "nbluew", "name": "Blue (W)", "rating": 76.2, "slope": 131, "yds": [490, 175, 564, 422, 176, 372, 441, 184, 422, 512, 355, 192, 344, 524, 139, 352, 317, 297]}, {"id": "nwhitew", "name": "White (W)", "rating": 74.1, "slope": 126, "yds": [478, 163, 530, 394, 168, 348, 396, 171, 358, 478, 327, 154, 326, 517, 130, 349, 303, 284]}, {"id": "nyelloww", "name": "Yellow (W)", "rating": 70.7, "slope": 121, "yds": [405, 152, 498, 344, 146, 328, 353, 140, 344, 394, 310, 148, 285, 437, 115, 340, 298, 267]}, {"id": "nredw", "name": "Red (W)", "rating": 67.7, "slope": 112, "yds": [400, 105, 460, 298, 106, 316, 318, 125, 296, 390, 293, 140, 280, 427, 109, 246, 259, 204]}], "holes": [{"par": 5, "si": 5}, {"par": 3, "si": 13}, {"par": 5, "si": 9}, {"par": 4, "si": 3}, {"par": 3, "si": 17}, {"par": 4, "si": 15}, {"par": 4, "si": 7}, {"par": 3, "si": 11}, {"par": 4, "si": 1}, {"par": 5, "si": 2}, {"par": 4, "si": 14}, {"par": 3, "si": 8}, {"par": 4, "si": 12}, {"par": 5, "si": 4}, {"par": 3, "si": 10}, {"par": 4, "si": 18}, {"par": 4, "si": 6}, {"par": 4, "si": 16}], "tier": "gps", "geoUrl": "geo/nat/iowa/10465.json", "nVerified": 16, "solved": false}