{"id": "nat1216", "name": "Les Bolstad Golf Course", "loc": [44.99258, -93.1921], "state": "Minnesota", "teeSets": [{"id": "nmaroon", "name": "Maroon", "rating": 70.4, "slope": 126, "yds": [370, 190, 386, 359, 167, 326, 476, 195, 480, 344, 356, 417, 536, 310, 390, 377, 145, 435]}, {"id": "nwhite", "name": "White", "rating": 69.3, "slope": 123, "yds": [363, 175, 370, 355, 159, 306, 464, 185, 472, 339, 347, 411, 525, 280, 390, 374, 135, 409]}, {"id": "nwhitegol", "name": "White Gold Combo", "rating": 68, "slope": 120, "yds": [345, 140, 370, 355, 159, 306, 450, 178, 472, 339, 347, 351, 430, 280, 390, 314, 135, 396]}, {"id": "ngold", "name": "Gold", "rating": 66.3, "slope": 117, "yds": [345, 140, 352, 340, 135, 294, 450, 178, 444, 281, 268, 351, 430, 268, 305, 314, 120, 396]}, {"id": "nmaroonw", "name": "Maroon (W)", "rating": 76.4, "slope": 131, "yds": [370, 190, 386, 359, 167, 326, 476, 195, 480, 344, 356, 417, 536, 310, 390, 377, 145, 435]}, {"id": "nwhitew", "name": "White (W)", "rating": 75.3, "slope": 128, "yds": [363, 175, 370, 355, 159, 306, 464, 185, 472, 339, 347, 411, 525, 280, 390, 374, 135, 409]}, {"id": "nwhitegolw", "name": "White Gold Combo (W)", "rating": 73.6, "slope": 125, "yds": [345, 140, 370, 355, 159, 306, 450, 178, 472, 339, 347, 351, 430, 280, 390, 314, 135, 396]}, {"id": "ngoldw", "name": "Gold (W)", "rating": 71.6, "slope": 121, "yds": [345, 140, 352, 340, 135, 294, 450, 178, 444, 281, 268, 351, 430, 268, 305, 314, 120, 396]}], "holes": [{"par": 4, "si": 4}, {"par": 3, "si": 10}, {"par": 4, "si": 6}, {"par": 4, "si": 2}, {"par": 3, "si": 16}, {"par": 4, "si": 18}, {"par": 5, "si": 12}, {"par": 3, "si": 8}, {"par": 5, "si": 14}, {"par": 4, "si": 11}, {"par": 4, "si": 13}, {"par": 4, "si": 1}, {"par": 5, "si": 9}, {"par": 4, "si": 17}, {"par": 4, "si": 3}, {"par": 4, "si": 5}, {"par": 3, "si": 15}, {"par": 4, "si": 7}], "tier": "gps", "geoUrl": "geo/nat/minnesota/1216.json", "nVerified": 17, "solved": false}