{"id": "nat11645", "name": "Meridian Golf Club", "loc": [39.54368, -104.85741], "state": "Colorado", "teeSets": [{"id": "ngold", "name": "Gold", "rating": 74.9, "slope": 147, "yds": [441, 400, 173, 430, 401, 594, 439, 212, 577, 359, 552, 447, 593, 422, 202, 416, 224, 458]}, {"id": "nblack", "name": "Black", "rating": 73.3, "slope": 145, "yds": [408, 395, 163, 397, 401, 553, 411, 199, 550, 355, 548, 418, 589, 422, 180, 392, 203, 420]}, {"id": "nblackblu", "name": "Black/Blue", "rating": 71.7, "slope": 140, "yds": [408, 395, 163, 384, 349, 553, 386, 186, 550, 355, 548, 397, 573, 381, 180, 392, 171, 366]}, {"id": "nblue", "name": "Blue", "rating": 70.4, "slope": 131, "yds": [396, 339, 150, 384, 349, 505, 386, 186, 499, 318, 504, 397, 573, 381, 150, 354, 171, 366]}, {"id": "nbluewhit", "name": "Blue/White", "rating": 69, "slope": 126, "yds": [368, 339, 150, 370, 332, 496, 374, 174, 499, 318, 504, 308, 481, 381, 150, 343, 171, 347]}, {"id": "nwhite", "name": "White", "rating": 68, "slope": 124, "yds": [368, 310, 107, 370, 332, 496, 374, 174, 469, 315, 474, 308, 481, 365, 147, 343, 139, 347]}, {"id": "nred", "name": "Red", "rating": 64.6, "slope": 113, "yds": [349, 275, 90, 209, 307, 406, 315, 137, 437, 300, 443, 275, 439, 309, 135, 305, 104, 305]}, {"id": "nblackw", "name": "Black (W)", "rating": 80.2, "slope": 153, "yds": [410, 396, 164, 387, 402, 553, 406, 210, 550, 359, 559, 419, 591, 425, 173, 410, 203, 419]}, {"id": "nbluew", "name": "Blue (W)", "rating": 76.5, "slope": 150, "yds": [396, 339, 150, 384, 349, 505, 386, 186, 499, 318, 504, 397, 573, 381, 150, 354, 171, 366]}, {"id": "nbluewhitw", "name": "Blue/White (W)", "rating": 74.6, "slope": 145, "yds": [368, 339, 150, 370, 332, 496, 374, 174, 499, 318, 504, 308, 481, 381, 150, 343, 171, 347]}], "holes": [{"par": 4, "si": 3}, {"par": 4, "si": 15}, {"par": 3, "si": 17}, {"par": 4, "si": 9}, {"par": 4, "si": 11}, {"par": 5, "si": 7}, {"par": 4, "si": 1}, {"par": 3, "si": 5}, {"par": 5, "si": 13}, {"par": 4, "si": 18}, {"par": 5, "si": 12}, {"par": 4, "si": 4}, {"par": 5, "si": 2}, {"par": 4, "si": 10}, {"par": 3, "si": 14}, {"par": 4, "si": 6}, {"par": 3, "si": 16}, {"par": 4, "si": 8}], "tier": "gps", "geoUrl": "geo/nat/colorado/11645.json", "nVerified": 17, "solved": false}