{"id": "nat1716", "name": "Northfield Golf Club", "loc": [42.70284, -72.44644], "state": "Massachusetts", "teeSets": [{"id": "nwhiteblu", "name": "WHITE/BLUE", "rating": 67.4, "slope": 116, "yds": [425, 288, 361, 252, 445, 162, 131, 270, 361, 434, 301, 376, 268, 455, 175, 143, 277, 380]}, {"id": "nredredme", "name": "RED/RED MEN", "rating": 63.4, "slope": 110, "yds": [392, 222, 252, 252, 370, 150, 118, 270, 312, 392, 222, 252, 252, 370, 150, 118, 270, 312]}, {"id": "nredredw", "name": "RED/RED (W)", "rating": 67.6, "slope": 129, "yds": [392, 222, 252, 252, 370, 150, 118, 270, 312, 392, 222, 252, 252, 370, 150, 118, 270, 312]}], "holes": [{"par": 5, "si": 9}, {"par": 4, "si": 11}, {"par": 4, "si": 1}, {"par": 4, "si": 17}, {"par": 5, "si": 7}, {"par": 3, "si": 5}, {"par": 3, "si": 13}, {"par": 4, "si": 15}, {"par": 4, "si": 3}], "tier": "gps", "geoUrl": "geo/nat/massachusett/1716.json", "nVerified": 9, "solved": false}