{"id": "nat2822", "name": "Cobleskill Golf Country Club", "loc": [42.67704, -74.45134], "state": "New York", "teeSets": [{"id": "nblue", "name": "Blue", "rating": 69.1, "slope": 128, "yds": [407, 156, 364, 340, 317, 530, 383, 106, 495, 216, 509, 430, 334, 169, 350, 375, 170, 337]}, {"id": "nwhite", "name": "White", "rating": 67.6, "slope": 125, "yds": [402, 146, 336, 330, 317, 521, 360, 100, 483, 180, 502, 394, 328, 159, 343, 369, 163, 312]}, {"id": "nsilver", "name": "Silver", "rating": 64.9, "slope": 111, "yds": [396, 139, 284, 326, 282, 451, 324, 94, 460, 178, 407, 330, 326, 150, 246, 305, 120, 282]}, {"id": "nred", "name": "Red", "rating": 64.5, "slope": 108, "yds": [390, 132, 251, 322, 282, 433, 321, 88, 456, 214, 404, 331, 240, 146, 242, 305, 115, 282]}, {"id": "nwhitew", "name": "White (W)", "rating": 73.4, "slope": 130, "yds": [402, 146, 336, 330, 317, 521, 360, 100, 483, 180, 502, 394, 328, 159, 343, 369, 163, 312]}, {"id": "nsilverw", "name": "Silver (W)", "rating": 69.4, "slope": 121, "yds": [396, 139, 284, 326, 282, 451, 324, 94, 460, 178, 407, 330, 326, 150, 246, 305, 120, 282]}, {"id": "nredw", "name": "Red (W)", "rating": 68.8, "slope": 119, "yds": [390, 132, 251, 322, 282, 433, 321, 88, 456, 214, 404, 331, 240, 146, 242, 305, 115, 282]}], "holes": [{"par": 4, "si": 12}, {"par": 3, "si": 14}, {"par": 4, "si": 6}, {"par": 4, "si": 16}, {"par": 4, "si": 8}, {"par": 5, "si": 4}, {"par": 4, "si": 2}, {"par": 3, "si": 18}, {"par": 5, "si": 10}, {"par": 3, "si": 17}, {"par": 5, "si": 3}, {"par": 4, "si": 1}, {"par": 4, "si": 7}, {"par": 3, "si": 11}, {"par": 4, "si": 13}, {"par": 4, "si": 5}, {"par": 3, "si": 9}, {"par": 4, "si": 15}], "tier": "gps", "geoUrl": "geo/nat/ny/2822.json", "nVerified": 15, "solved": false}