{"id": "nat2372", "name": "Westport Country Club", "loc": [44.18023, -73.44187], "state": "New York", "teeSets": [{"id": "ngreen", "name": "Green", "rating": 72.1, "slope": 140, "yds": [426, 321, 526, 145, 537, 393, 361, 440, 200, 396, 518, 420, 203, 363, 381, 173, 440, 367]}, {"id": "nwhite", "name": "White", "rating": 70.5, "slope": 135, "yds": [390, 311, 461, 138, 486, 352, 353, 431, 181, 362, 510, 410, 194, 355, 357, 162, 428, 347]}, {"id": "ngold", "name": "Gold", "rating": 67.5, "slope": 122, "yds": [365, 309, 452, 132, 479, 345, 273, 293, 174, 255, 427, 358, 123, 343, 348, 150, 397, 335]}, {"id": "nredw", "name": "Red (W)", "rating": 69.7, "slope": 126, "yds": [350, 280, 422, 125, 442, 308, 270, 293, 169, 251, 422, 349, 115, 250, 338, 112, 386, 239]}], "holes": [{"par": 4, "si": 5}, {"par": 4, "si": 17}, {"par": 5, "si": 3}, {"par": 3, "si": 15}, {"par": 5, "si": 11}, {"par": 4, "si": 9}, {"par": 4, "si": 7}, {"par": 4, "si": 1}, {"par": 3, "si": 13}, {"par": 4, "si": 10}, {"par": 5, "si": 4}, {"par": 4, "si": 6}, {"par": 3, "si": 12}, {"par": 4, "si": 14}, {"par": 4, "si": 16}, {"par": 3, "si": 18}, {"par": 5, "si": 2}, {"par": 4, "si": 8}], "tier": "gps", "geoUrl": "geo/nat/ny/2372.json", "nVerified": 17, "solved": false}