{"id": "nat2232", "name": "Ingersoll Golf Course", "loc": [42.27394, -89.15333], "state": "Illinois", "teeSets": [{"id": "nback", "name": "Back", "rating": 69.5, "slope": 120, "yds": [382, 521, 221, 323, 376, 414, 388, 415, 336, 331, 341, 254, 378, 400, 122, 282, 471, 301]}, {"id": "nmiddle", "name": "Middle", "rating": 68.8, "slope": 118, "yds": [366, 508, 216, 319, 371, 406, 378, 403, 330, 323, 337, 233, 368, 384, 118, 279, 468, 294]}, {"id": "nfront", "name": "Front", "rating": 67.7, "slope": 115, "yds": [351, 493, 205, 310, 355, 393, 366, 390, 312, 301, 324, 218, 363, 374, 108, 270, 457, 280]}, {"id": "nbackw", "name": "Back (W)", "rating": 76.2, "slope": 129, "yds": [382, 521, 221, 323, 376, 414, 388, 415, 336, 331, 341, 254, 378, 400, 122, 282, 471, 301]}, {"id": "nmiddlew", "name": "Middle (W)", "rating": 75.3, "slope": 127, "yds": [366, 508, 216, 319, 371, 406, 378, 403, 330, 323, 337, 233, 368, 384, 118, 279, 468, 294]}, {"id": "nfrontw", "name": "Front (W)", "rating": 73.9, "slope": 124, "yds": [351, 493, 205, 310, 355, 393, 366, 390, 312, 301, 324, 218, 363, 374, 108, 270, 457, 280]}], "holes": [{"par": 4, "si": 11}, {"par": 5, "si": 1}, {"par": 3, "si": 17}, {"par": 4, "si": 13}, {"par": 4, "si": 7}, {"par": 4, "si": 5}, {"par": 4, "si": 9}, {"par": 4, "si": 3}, {"par": 4, "si": 15}, {"par": 4, "si": 10}, {"par": 4, "si": 6}, {"par": 3, "si": 16}, {"par": 4, "si": 4}, {"par": 4, "si": 8}, {"par": 3, "si": 18}, {"par": 4, "si": 14}, {"par": 5, "si": 2}, {"par": 4, "si": 12}], "tier": "gps", "geoUrl": "geo/nat/il/2232.json", "nVerified": 7, "solved": false}