{"id": "nat360", "name": "Tedesco Country Club", "loc": [42.47874, -70.90138], "state": "xx", "teeSets": [{"id": "nblack", "name": "BLACK", "rating": 71.8, "slope": 134, "yds": [432, 394, 199, 423, 368, 277, 238, 134, 505, 553, 368, 368, 143, 364, 376, 454, 423, 435]}, {"id": "nblue", "name": "BLUE", "rating": 70.4, "slope": 132, "yds": [427, 386, 177, 416, 348, 274, 229, 131, 495, 521, 331, 325, 137, 354, 372, 440, 410, 425]}, {"id": "nbluewhit", "name": "BLUE/WHITE", "rating": 69.1, "slope": 131, "yds": [427, 365, 177, 369, 348, 274, 229, 131, 495, 521, 331, 325, 137, 354, 372, 385, 350, 379]}, {"id": "nwhite", "name": "WHITE", "rating": 67.1, "slope": 125, "yds": [424, 365, 164, 369, 321, 270, 148, 130, 430, 512, 288, 258, 125, 321, 278, 385, 350, 379]}, {"id": "nsilver", "name": "SILVER", "rating": 66.2, "slope": 121, "yds": [422, 336, 151, 368, 274, 270, 148, 90, 428, 508, 286, 258, 123, 319, 276, 383, 346, 377]}, {"id": "nyellow", "name": "YELLOW", "rating": 64.5, "slope": 117, "yds": [420, 333, 148, 363, 269, 266, 148, 86, 426, 432, 267, 255, 121, 276, 274, 278, 328, 372]}, {"id": "nintermed", "name": "INTERMEDIATE", "rating": 61.6, "slope": 105, "yds": [420, 234, 148, 266, 269, 220, 148, 86, 331, 360, 267, 255, 121, 195, 220, 278, 270, 254]}, {"id": "nblackw", "name": "BLACK (W)", "rating": 78, "slope": 147, "yds": [432, 394, 199, 423, 368, 277, 238, 134, 505, 553, 368, 368, 143, 364, 376, 454, 423, 435]}, {"id": "nbluew", "name": "BLUE (W)", "rating": 76.5, "slope": 144, "yds": [427, 386, 177, 416, 348, 274, 229, 131, 495, 521, 331, 325, 137, 354, 372, 440, 410, 425]}, {"id": "nbluewhitw", "name": "BLUE/WHITE (W)", "rating": 75.3, "slope": 142, "yds": [427, 365, 177, 369, 348, 274, 229, 131, 495, 521, 331, 325, 137, 354, 372, 385, 350, 379]}], "holes": [{"par": 4, "si": 6}, {"par": 4, "si": 10}, {"par": 3, "si": 18}, {"par": 4, "si": 2}, {"par": 4, "si": 8}, {"par": 4, "si": 12}, {"par": 3, "si": 14}, {"par": 3, "si": 16}, {"par": 5, "si": 4}, {"par": 5, "si": 5}, {"par": 4, "si": 15}, {"par": 4, "si": 3}, {"par": 3, "si": 17}, {"par": 4, "si": 11}, {"par": 4, "si": 7}, {"par": 4, "si": 1}, {"par": 4, "si": 9}, {"par": 4, "si": 13}], "tier": "gps", "geoUrl": "geo/nat/xx/360.json", "nVerified": 18, "solved": false}