{"id": "nat495", "name": "Mount Pleasant Golf Club", "loc": [42.62502, -71.34668], "state": "Massachusetts", "teeSets": [{"id": "nyellowbl", "name": "YELLOW/BLACK", "rating": 70.8, "slope": 127, "yds": [360, 393, 384, 460, 280, 172, 142, 501, 399, 375, 410, 396, 475, 283, 194, 150, 528, 410]}, {"id": "ngreenyel", "name": "GREEN/YELLOW", "rating": 69.2, "slope": 124, "yds": [350, 382, 372, 423, 276, 160, 126, 484, 390, 360, 393, 384, 460, 280, 172, 142, 501, 399]}, {"id": "nsilvergr", "name": "SILVER/GREEN", "rating": 67.8, "slope": 122, "yds": [350, 373, 362, 412, 270, 145, 123, 472, 325, 350, 382, 372, 423, 276, 160, 126, 484, 390]}, {"id": "nbluesilv", "name": "BLUE/SILVER", "rating": 66.4, "slope": 117, "yds": [280, 365, 356, 400, 264, 135, 114, 460, 260, 350, 373, 362, 412, 270, 145, 123, 472, 325]}, {"id": "nyellowblw", "name": "YELLOW/BLACK (W)", "rating": 77.6, "slope": 137, "yds": [360, 393, 384, 460, 280, 172, 142, 501, 399, 375, 410, 396, 475, 283, 194, 150, 528, 410]}, {"id": "ngreenyelw", "name": "GREEN/YELLOW (W)", "rating": 75.7, "slope": 135, "yds": [350, 382, 372, 423, 276, 160, 126, 484, 390, 360, 393, 384, 460, 280, 172, 142, 501, 399]}, {"id": "nbluegreew", "name": "BLUE/GREEN (W)", "rating": 72.4, "slope": 129, "yds": [280, 365, 356, 400, 264, 135, 114, 460, 260, 350, 382, 372, 423, 276, 160, 126, 484, 390]}, {"id": "nbluesilvw", "name": "BLUE/SILVER (W)", "rating": 71.5, "slope": 126, "yds": [280, 365, 356, 400, 264, 135, 114, 460, 260, 350, 373, 362, 412, 270, 145, 123, 472, 325]}], "holes": [{"par": 4, "si": 10}, {"par": 4, "si": 4}, {"par": 4, "si": 2}, {"par": 5, "si": 12}, {"par": 4, "si": 14}, {"par": 3, "si": 16}, {"par": 3, "si": 18}, {"par": 5, "si": 8}, {"par": 4, "si": 6}], "tier": "gps", "geoUrl": "geo/nat/massachusett/495.json", "nVerified": 9, "solved": false}