{"id": "nat4773", "name": "Broken Tee Golf Course", "loc": [39.64818, -105.01482], "state": "Colorado", "teeSets": [{"id": "ngreen", "name": "Green", "rating": 72, "slope": 136, "yds": [328, 431, 397, 344, 194, 538, 202, 406, 545, 151, 402, 397, 548, 366, 499, 414, 189, 446]}, {"id": "nbluegree", "name": "Blue/Green - EMGC Only", "rating": 71.7, "slope": 135, "yds": [328, 431, 397, 344, 169, 538, 173, 406, 545, 151, 402, 397, 548, 366, 499, 414, 166, 446]}, {"id": "nbluegree2", "name": "Blue/Green", "rating": 70.3, "slope": 128, "yds": [298, 380, 360, 304, 169, 490, 173, 362, 508, 151, 402, 397, 548, 366, 499, 414, 189, 446]}, {"id": "nblue", "name": "Blue", "rating": 70, "slope": 124, "yds": [298, 380, 360, 304, 169, 490, 173, 362, 508, 140, 393, 373, 538, 346, 491, 398, 166, 418]}, {"id": "nredbluee", "name": "Red/Blue - EMGC Only", "rating": 69.7, "slope": 123, "yds": [298, 380, 360, 304, 169, 490, 160, 362, 508, 140, 393, 373, 538, 346, 491, 398, 137, 418]}, {"id": "nredblue", "name": "Red/Blue", "rating": 68.6, "slope": 116, "yds": [270, 324, 320, 278, 110, 453, 160, 324, 474, 140, 393, 373, 538, 346, 491, 398, 166, 418]}, {"id": "nred", "name": "Red", "rating": 67.6, "slope": 114, "yds": [270, 324, 320, 278, 110, 453, 160, 324, 474, 129, 387, 363, 528, 328, 483, 334, 137, 408]}, {"id": "nblackred", "name": "Black/Red", "rating": 65.8, "slope": 110, "yds": [227, 283, 249, 193, 110, 411, 128, 289, 407, 129, 387, 363, 528, 328, 483, 334, 137, 408]}, {"id": "nblack", "name": "Black", "rating": 65.7, "slope": 107, "yds": [227, 283, 249, 213, 110, 411, 128, 289, 407, 118, 385, 352, 519, 322, 475, 328, 129, 399]}, {"id": "nblackwhi", "name": "Black/White", "rating": 63.4, "slope": 103, "yds": [227, 283, 249, 213, 110, 411, 128, 289, 407, 118, 272, 286, 429, 322, 394, 279, 129, 303]}], "holes": [{"par": 4, "si": 11}, {"par": 4, "si": 5}, {"par": 4, "si": 13}, {"par": 4, "si": 3}, {"par": 3, "si": 15}, {"par": 5, "si": 1}, {"par": 3, "si": 17}, {"par": 4, "si": 7}, {"par": 5, "si": 9}, {"par": 3, "si": 18}, {"par": 4, "si": 12}, {"par": 4, "si": 8}, {"par": 5, "si": 2}, {"par": 4, "si": 14}, {"par": 5, "si": 10}, {"par": 4, "si": 4}, {"par": 3, "si": 16}, {"par": 4, "si": 6}], "tier": "gps", "geoUrl": "geo/nat/colorado/4773.json", "nVerified": 13, "solved": false}