{"id": "nat4692", "name": "Trails of Frisco Golf Course", "loc": [33.17079, -96.87114], "state": "Texas", "teeSets": [{"id": "nchampion", "name": "Championship", "rating": 74.7, "slope": 140, "yds": [562, 468, 208, 378, 453, 178, 555, 361, 420, 533, 157, 462, 351, 226, 431, 162, 468, 576]}, {"id": "nblue", "name": "Blue", "rating": 71.4, "slope": 131, "yds": [522, 430, 171, 342, 426, 147, 501, 333, 373, 491, 135, 435, 335, 204, 398, 141, 396, 537]}, {"id": "nwhite", "name": "White", "rating": 69.3, "slope": 127, "yds": [486, 384, 147, 311, 394, 128, 448, 313, 342, 461, 114, 418, 305, 179, 370, 118, 361, 498]}, {"id": "nred", "name": "Red", "rating": 66, "slope": 116, "yds": [436, 322, 110, 286, 359, 98, 428, 207, 307, 390, 87, 393, 273, 160, 358, 103, 327, 460]}, {"id": "nchampionw", "name": "Championship (W)", "rating": 82.4, "slope": 154, "yds": [562, 468, 208, 378, 453, 178, 555, 361, 420, 533, 157, 462, 351, 226, 431, 162, 468, 576]}, {"id": "nbluew", "name": "Blue (W)", "rating": 78.2, "slope": 150, "yds": [522, 430, 171, 342, 426, 147, 501, 333, 373, 491, 135, 435, 335, 204, 398, 141, 396, 537]}, {"id": "nwhitew", "name": "White (W)", "rating": 74.8, "slope": 138, "yds": [486, 384, 147, 311, 394, 128, 448, 313, 342, 461, 114, 418, 305, 179, 370, 118, 361, 498]}, {"id": "nredw", "name": "Red (W)", "rating": 71.4, "slope": 125, "yds": [436, 322, 110, 286, 359, 98, 428, 207, 307, 390, 87, 393, 273, 160, 358, 103, 327, 460]}], "holes": [{"par": 5, "si": 7}, {"par": 4, "si": 1}, {"par": 3, "si": 9}, {"par": 4, "si": 13}, {"par": 4, "si": 3}, {"par": 3, "si": 17}, {"par": 5, "si": 11}, {"par": 4, "si": 15}, {"par": 4, "si": 5}, {"par": 5, "si": 12}, {"par": 3, "si": 18}, {"par": 4, "si": 4}, {"par": 4, "si": 16}, {"par": 3, "si": 8}, {"par": 4, "si": 2}, {"par": 3, "si": 14}, {"par": 4, "si": 6}, {"par": 5, "si": 10}], "tier": "gps", "geoUrl": "geo/nat/tx/4692.json", "nVerified": 16, "solved": false}