{"id": "nat4463", "name": "Silverbell Golf Course", "loc": [32.27264, -111.0204], "state": "Arizona", "teeSets": [{"id": "nblue", "name": "Blue", "rating": 71.6, "slope": 124, "yds": [463, 541, 150, 494, 386, 214, 577, 447, 191, 373, 371, 194, 428, 455, 338, 233, 399, 555]}, {"id": "nbluewhit", "name": "Blue/White", "rating": 70.3, "slope": 123, "yds": [424, 541, 150, 456, 386, 185, 577, 391, 171, 373, 371, 172, 419, 427, 338, 211, 399, 555]}, {"id": "nwhite", "name": "White", "rating": 68.9, "slope": 121, "yds": [424, 503, 141, 456, 360, 185, 531, 391, 171, 327, 353, 172, 419, 427, 304, 211, 373, 546]}, {"id": "nwhiteyel", "name": "White/Yellow", "rating": 67.7, "slope": 118, "yds": [387, 503, 141, 429, 360, 163, 531, 391, 171, 327, 353, 165, 393, 354, 304, 181, 318, 546]}, {"id": "nyellow", "name": "Yellow", "rating": 66.7, "slope": 114, "yds": [387, 484, 127, 429, 341, 163, 509, 354, 151, 309, 335, 165, 393, 354, 248, 181, 318, 519]}, {"id": "nyellowre", "name": "Yellow/Red", "rating": 65.4, "slope": 110, "yds": [356, 484, 127, 405, 341, 134, 471, 354, 151, 309, 335, 138, 371, 354, 248, 159, 318, 472]}, {"id": "nred", "name": "Red", "rating": 63.7, "slope": 105, "yds": [356, 420, 117, 405, 322, 134, 471, 341, 123, 291, 273, 138, 371, 300, 214, 159, 286, 472]}, {"id": "nwhitew", "name": "White (W)", "rating": 74.9, "slope": 131, "yds": [440, 522, 143, 455, 336, 186, 548, 395, 177, 335, 378, 178, 420, 430, 316, 214, 380, 538]}, {"id": "nwhiteyelw", "name": "White/Yellow (W)", "rating": 73.2, "slope": 126, "yds": [387, 522, 143, 429, 336, 163, 548, 395, 177, 335, 378, 165, 393, 354, 316, 181, 318, 538]}, {"id": "nyelloww", "name": "Yellow (W)", "rating": 72.1, "slope": 122, "yds": [387, 484, 127, 429, 341, 163, 509, 354, 151, 309, 335, 165, 393, 354, 248, 181, 318, 519]}], "holes": [{"par": 4, "si": 5}, {"par": 5, "si": 3}, {"par": 3, "si": 17}, {"par": 4, "si": 9}, {"par": 4, "si": 13}, {"par": 3, "si": 11}, {"par": 5, "si": 1}, {"par": 4, "si": 7}, {"par": 3, "si": 15}, {"par": 4, "si": 14}, {"par": 4, "si": 10}, {"par": 3, "si": 18}, {"par": 4, "si": 8}, {"par": 4, "si": 4}, {"par": 4, "si": 16}, {"par": 3, "si": 12}, {"par": 4, "si": 6}, {"par": 5, "si": 2}], "tier": "gps", "geoUrl": "geo/nat/arizona/4463.json", "nVerified": 18, "solved": false}