{"id": "nat5270", "name": "Bruce Hills Golf Course", "loc": [42.82779, -83.04895], "state": "Michigan", "teeSets": [{"id": "nwhite", "name": "WHITE", "rating": 67.5, "slope": 117, "yds": [271, 378, 191, 324, 371, 117, 555, 387, 360, 238, 156, 395, 139, 398, 296, 358, 151, 465]}, {"id": "nred", "name": "RED", "rating": 63.7, "slope": 106, "yds": [223, 293, 152, 292, 345, 92, 464, 333, 301, 217, 125, 352, 111, 317, 253, 330, 85, 372]}, {"id": "nwhitew", "name": "WHITE (W)", "rating": 73.1, "slope": 126, "yds": [271, 378, 191, 324, 371, 117, 555, 387, 360, 238, 156, 395, 139, 398, 296, 358, 151, 465]}, {"id": "nredw", "name": "RED (W)", "rating": 67.6, "slope": 111, "yds": [223, 293, 152, 292, 345, 92, 464, 333, 301, 217, 125, 352, 111, 317, 253, 330, 85, 372]}], "holes": [{"par": 4, "si": 15}, {"par": 4, "si": 5}, {"par": 3, "si": 11}, {"par": 4, "si": 13}, {"par": 4, "si": 1}, {"par": 3, "si": 17}, {"par": 5, "si": 7}, {"par": 4, "si": 3}, {"par": 4, "si": 9}, {"par": 4, "si": 4}, {"par": 3, "si": 10}, {"par": 5, "si": 16}, {"par": 3, "si": 14}, {"par": 4, "si": 2}, {"par": 4, "si": 18}, {"par": 4, "si": 6}, {"par": 3, "si": 8}, {"par": 5, "si": 12}], "tier": "gps", "geoUrl": "geo/nat/mi/5270.json", "nVerified": 18, "solved": false}