{"id": "nat5567", "name": "Whispering Hills Golf Course", "loc": [39.73608, -85.97832], "state": "Indiana", "teeSets": [{"id": "nblue", "name": "Blue", "rating": 64.6, "slope": 114, "yds": [305, 172, 357, 322, 147, 472, 350, 284, 175, 305, 172, 357, 322, 147, 472, 350, 284, 175]}, {"id": "nwhite", "name": "White", "rating": 62.8, "slope": 102, "yds": [281, 144, 326, 293, 117, 445, 319, 266, 149, 281, 144, 326, 293, 117, 445, 319, 266, 149]}, {"id": "nred", "name": "Red", "rating": 60.2, "slope": 91, "yds": [257, 122, 285, 225, 80, 408, 296, 216, 119, 257, 122, 285, 225, 80, 408, 296, 216, 119]}, {"id": "nbluew", "name": "Blue (W)", "rating": 69.8, "slope": 122, "yds": [305, 172, 357, 322, 147, 472, 350, 284, 175, 305, 172, 357, 322, 147, 472, 350, 284, 175]}, {"id": "nwhitew", "name": "White (W)", "rating": 66.4, "slope": 121, "yds": [281, 144, 326, 293, 117, 445, 319, 266, 149, 281, 144, 326, 293, 117, 445, 319, 266, 149]}, {"id": "nredw", "name": "Red (W)", "rating": 62, "slope": 109, "yds": [257, 122, 285, 225, 80, 408, 296, 216, 119, 257, 122, 285, 225, 80, 408, 296, 216, 119]}], "holes": [{"par": 4, "si": 17}, {"par": 3, "si": 9}, {"par": 4, "si": 3}, {"par": 4, "si": 7}, {"par": 3, "si": 1}, {"par": 5, "si": 15}, {"par": 4, "si": 11}, {"par": 4, "si": 13}, {"par": 3, "si": 5}], "tier": "gps", "geoUrl": "geo/nat/indiana/5567.json", "nVerified": 9, "solved": false}