{"id": "nat5329", "name": "Chemung Hills Golf Club", "loc": [42.60355, -83.88871], "state": "Michigan", "teeSets": [{"id": "nblue", "name": "BLUE", "rating": 72.2, "slope": 132, "yds": [453, 358, 341, 188, 379, 390, 306, 289, 395, 528, 142, 365, 421, 389, 492, 302, 389, 203]}, {"id": "nwhite", "name": "WHITE", "rating": 70.1, "slope": 127, "yds": [441, 346, 325, 165, 369, 356, 298, 283, 385, 473, 136, 356, 406, 352, 486, 289, 377, 128]}, {"id": "nblack", "name": "BLACK", "rating": 66.3, "slope": 120, "yds": [351, 298, 254, 145, 343, 316, 292, 276, 356, 335, 131, 289, 369, 327, 453, 249, 341, 120]}, {"id": "nred", "name": "RED", "rating": 63.7, "slope": 114, "yds": [346, 288, 247, 126, 337, 191, 286, 270, 287, 327, 129, 281, 294, 319, 321, 242, 274, 110]}, {"id": "nbluew", "name": "BLUE (W)", "rating": 77.6, "slope": 145, "yds": [453, 358, 341, 188, 379, 390, 306, 289, 395, 528, 142, 365, 421, 389, 492, 302, 389, 203]}, {"id": "nwhitew", "name": "WHITE (W)", "rating": 75.7, "slope": 142, "yds": [441, 346, 325, 165, 369, 356, 298, 283, 385, 473, 136, 356, 406, 352, 486, 289, 377, 128]}, {"id": "nblackw", "name": "BLACK (W)", "rating": 72, "slope": 124, "yds": [351, 298, 254, 145, 343, 316, 292, 276, 356, 335, 131, 289, 369, 327, 453, 249, 341, 120]}, {"id": "nredw", "name": "RED (W)", "rating": 68.7, "slope": 118, "yds": [346, 288, 247, 126, 337, 191, 286, 270, 287, 327, 129, 281, 294, 319, 321, 242, 274, 110]}], "holes": [{"par": 5, "si": 10}, {"par": 4, "si": 6}, {"par": 4, "si": 12}, {"par": 3, "si": 18}, {"par": 4, "si": 4}, {"par": 4, "si": 2}, {"par": 4, "si": 14}, {"par": 4, "si": 16}, {"par": 4, "si": 8}, {"par": 5, "si": 9}, {"par": 3, "si": 17}, {"par": 4, "si": 11}, {"par": 4, "si": 1}, {"par": 4, "si": 7}, {"par": 5, "si": 3}, {"par": 4, "si": 15}, {"par": 4, "si": 5}, {"par": 3, "si": 13}], "tier": "gps", "geoUrl": "geo/nat/mi/5329.json", "nVerified": 18, "solved": false}