{"id": "nat5304", "name": "Sanctuary Lake Golf Course", "loc": [42.61842, -83.10092], "state": "Michigan", "teeSets": [{"id": "nblack", "name": "BLACK", "rating": 70.8, "slope": 130, "yds": [413, 373, 446, 440, 183, 536, 133, 366, 178, 436, 502, 211, 421, 370, 169, 413, 277, 521]}, {"id": "nblue", "name": "BLUE", "rating": 69.2, "slope": 124, "yds": [399, 370, 436, 428, 167, 509, 128, 341, 157, 421, 467, 187, 380, 330, 149, 402, 258, 477]}, {"id": "nwhite", "name": "WHITE", "rating": 65.4, "slope": 109, "yds": [382, 324, 300, 391, 151, 482, 113, 317, 144, 392, 393, 168, 348, 259, 123, 332, 238, 437]}, {"id": "nred", "name": "RED", "rating": 62.8, "slope": 105, "yds": [365, 277, 264, 355, 135, 455, 98, 290, 97, 349, 362, 151, 317, 221, 112, 262, 219, 378]}, {"id": "nblackw", "name": "BLACK (W)", "rating": 77, "slope": 137, "yds": [413, 373, 446, 440, 183, 536, 133, 366, 178, 436, 502, 211, 421, 370, 169, 413, 277, 521]}, {"id": "nbluew", "name": "BLUE (W)", "rating": 74.9, "slope": 132, "yds": [399, 370, 436, 428, 167, 509, 128, 341, 157, 421, 467, 187, 380, 330, 149, 402, 258, 477]}, {"id": "nwhitew", "name": "WHITE (W)", "rating": 70.9, "slope": 123, "yds": [382, 324, 300, 391, 151, 482, 113, 317, 144, 392, 393, 168, 348, 259, 123, 332, 238, 437]}, {"id": "nredw", "name": "RED (W)", "rating": 67, "slope": 119, "yds": [365, 277, 264, 355, 135, 455, 98, 290, 97, 349, 362, 151, 317, 221, 112, 262, 219, 378]}], "holes": [{"par": 4, "si": 3}, {"par": 4, "si": 13}, {"par": 5, "si": 17}, {"par": 4, "si": 1}, {"par": 3, "si": 9}, {"par": 5, "si": 7}, {"par": 3, "si": 15}, {"par": 4, "si": 5}, {"par": 3, "si": 11}, {"par": 4, "si": 8}, {"par": 5, "si": 16}, {"par": 3, "si": 14}, {"par": 4, "si": 12}, {"par": 4, "si": 2}, {"par": 3, "si": 10}, {"par": 4, "si": 4}, {"par": 4, "si": 18}, {"par": 5, "si": 6}], "tier": "gps", "geoUrl": "geo/nat/mi/5304.json", "nVerified": 18, "solved": false}