{"id": "nat5436", "name": "Riverview Highlands Golf Course", "loc": [42.17317, -83.20802], "state": "Michigan", "teeSets": [{"id": "nblue", "name": "BLUE", "rating": 72, "slope": 126, "yds": [405, 149, 512, 141, 368, 438, 514, 401, 292, 402, 491, 445, 206, 382, 554, 184, 323, 419]}, {"id": "nwhite", "name": "WHITE", "rating": 70, "slope": 123, "yds": [390, 122, 489, 106, 344, 424, 491, 387, 279, 394, 480, 403, 187, 372, 509, 154, 289, 376]}, {"id": "ngold", "name": "GOLD", "rating": 67.9, "slope": 117, "yds": [375, 108, 472, 92, 325, 400, 478, 324, 263, 386, 446, 388, 146, 362, 492, 144, 268, 364]}, {"id": "nred", "name": "RED", "rating": 65.3, "slope": 107, "yds": [363, 93, 456, 78, 306, 396, 466, 315, 250, 316, 352, 356, 137, 324, 421, 139, 236, 316]}, {"id": "nbluew", "name": "BLUE (W)", "rating": 79, "slope": 143, "yds": [405, 149, 512, 141, 368, 438, 514, 401, 292, 402, 491, 445, 206, 382, 554, 184, 323, 419]}, {"id": "nwhitew", "name": "WHITE (W)", "rating": 76.4, "slope": 133, "yds": [390, 122, 489, 106, 344, 424, 491, 387, 279, 394, 480, 403, 187, 372, 509, 154, 289, 376]}, {"id": "ngoldw", "name": "GOLD (W)", "rating": 74.1, "slope": 125, "yds": [375, 108, 472, 92, 325, 400, 478, 324, 263, 386, 446, 388, 146, 362, 492, 144, 268, 364]}, {"id": "nredw", "name": "RED (W)", "rating": 70.7, "slope": 120, "yds": [363, 93, 456, 78, 306, 396, 466, 315, 250, 316, 352, 356, 137, 324, 421, 139, 236, 316]}], "holes": [{"par": 4, "si": 7}, {"par": 3, "si": 13}, {"par": 5, "si": 9}, {"par": 3, "si": 15}, {"par": 4, "si": 11}, {"par": 4, "si": 3}, {"par": 5, "si": 5}, {"par": 4, "si": 1}, {"par": 4, "si": 17}, {"par": 4, "si": 6}, {"par": 5, "si": 8}, {"par": 4, "si": 2}, {"par": 3, "si": 12}, {"par": 4, "si": 16}, {"par": 5, "si": 10}, {"par": 3, "si": 18}, {"par": 4, "si": 14}, {"par": 4, "si": 4}], "tier": "gps", "geoUrl": "geo/nat/mi/5436.json", "nVerified": 10, "solved": false}