{"id": "nat6540", "name": "The Maplewood Golf Club", "loc": [44.28172, -71.66537], "state": "New Hampshire", "teeSets": [{"id": "nblue", "name": "Blue", "rating": 69, "slope": 121, "yds": [444, 369, 320, 374, 361, 397, 308, 138, 348, 337, 159, 192, 328, 264, 512, 646, 267, 138]}, {"id": "n2021whit", "name": "2021 White", "rating": 67.7, "slope": 119, "yds": [434, 366, 295, 363, 351, 363, 298, 127, 343, 330, 152, 187, 320, 242, 485, 620, 249, 142]}, {"id": "ngreen", "name": "Green", "rating": 64.8, "slope": 113, "yds": [381, 285, 280, 322, 351, 277, 298, 127, 309, 296, 152, 173, 320, 242, 407, 523, 249, 131]}, {"id": "nyellow", "name": "Yellow", "rating": 63.8, "slope": 108, "yds": [381, 285, 244, 322, 290, 277, 231, 117, 309, 296, 144, 173, 294, 232, 407, 523, 226, 131]}, {"id": "nwhitew", "name": "White (W)", "rating": 73.3, "slope": 124, "yds": [434, 366, 295, 363, 351, 363, 298, 127, 343, 330, 152, 187, 320, 242, 485, 620, 249, 142]}, {"id": "ngreenw", "name": "Green (W)", "rating": 70.1, "slope": 119, "yds": [381, 285, 280, 322, 351, 277, 298, 127, 309, 296, 152, 173, 320, 242, 407, 523, 249, 131]}, {"id": "nyelloww", "name": "Yellow (W)", "rating": 68.6, "slope": 116, "yds": [381, 285, 244, 322, 290, 277, 231, 117, 309, 296, 144, 173, 294, 232, 407, 523, 226, 131]}], "holes": [{"par": 5, "si": 11}, {"par": 4, "si": 1}, {"par": 4, "si": 9}, {"par": 4, "si": 7}, {"par": 4, "si": 5}, {"par": 4, "si": 3}, {"par": 4, "si": 15}, {"par": 3, "si": 17}, {"par": 4, "si": 13}, {"par": 4, "si": 4}, {"par": 3, "si": 12}, {"par": 3, "si": 14}, {"par": 4, "si": 8}, {"par": 4, "si": 10}, {"par": 5, "si": 2}, {"par": 6, "si": 6}, {"par": 4, "si": 18}, {"par": 3, "si": 16}], "tier": "gps", "geoUrl": "geo/nat/newhampshire/6540.json", "nVerified": 18, "solved": false}