{"id": "nat6330", "name": "Ayden Golf & Country Club", "loc": [35.46164, -77.38967], "state": "North Carolina", "teeSets": [{"id": "nbluetees", "name": "Blue Tees", "rating": 71.4, "slope": 131, "yds": [347, 533, 357, 155, 387, 370, 515, 381, 190, 523, 406, 204, 356, 297, 391, 392, 158, 603]}, {"id": "nwhitetee", "name": "White Tees", "rating": 69.7, "slope": 128, "yds": [335, 491, 341, 147, 368, 353, 497, 358, 170, 507, 385, 179, 336, 269, 372, 375, 146, 579]}, {"id": "ngreenhyb", "name": "Green Hybrid", "rating": 67.9, "slope": 117, "yds": [335, 491, 341, 147, 341, 335, 402, 334, 170, 459, 331, 179, 336, 269, 325, 336, 146, 479]}, {"id": "ngoldtees", "name": "Gold Tees", "rating": 67.1, "slope": 113, "yds": [322, 469, 324, 134, 341, 335, 402, 334, 154, 459, 331, 137, 315, 240, 325, 336, 128, 479]}, {"id": "nredtees", "name": "Red Tees", "rating": 64.4, "slope": 108, "yds": [276, 425, 263, 134, 287, 294, 389, 290, 154, 411, 300, 119, 272, 204, 282, 286, 128, 449]}, {"id": "norangete", "name": "Orange Tees", "rating": 60.8, "slope": 95, "yds": [276, 351, 263, 134, 217, 201, 311, 242, 118, 339, 217, 119, 232, 141, 205, 230, 128, 398]}, {"id": "nwhiteteew", "name": "White Tees (W)", "rating": 75.7, "slope": 134, "yds": [335, 491, 341, 147, 368, 353, 497, 358, 170, 507, 385, 179, 336, 269, 372, 375, 146, 579]}, {"id": "ngoldteesw", "name": "Gold Tees (W)", "rating": 72.1, "slope": 126, "yds": [322, 469, 324, 134, 341, 335, 402, 334, 154, 459, 331, 137, 315, 240, 325, 336, 128, 479]}, {"id": "nredteesw", "name": "Red Tees (W)", "rating": 69.3, "slope": 119, "yds": [276, 425, 263, 134, 287, 294, 389, 290, 154, 411, 300, 119, 272, 204, 282, 286, 128, 449]}, {"id": "norangetew", "name": "Orange Tees (W)", "rating": 63.8, "slope": 103, "yds": [276, 351, 263, 134, 217, 201, 311, 242, 118, 339, 217, 119, 232, 141, 205, 230, 128, 398]}], "holes": [{"par": 4, "si": 18}, {"par": 5, "si": 4}, {"par": 4, "si": 10}, {"par": 3, "si": 8}, {"par": 4, "si": 12}, {"par": 4, "si": 2}, {"par": 5, "si": 14}, {"par": 4, "si": 16}, {"par": 3, "si": 6}, {"par": 5, "si": 1}, {"par": 4, "si": 3}, {"par": 3, "si": 13}, {"par": 4, "si": 7}, {"par": 4, "si": 17}, {"par": 4, "si": 9}, {"par": 4, "si": 11}, {"par": 3, "si": 15}, {"par": 5, "si": 5}], "tier": "card", "geoUrl": null, "nVerified": 3, "solved": false}