{"id": "nat6619", "name": "Lady Bird Johnson Municipal Golf Course", "loc": [30.24503, -98.91571], "state": "Texas", "teeSets": [{"id": "nblack", "name": "Black", "rating": 72.2, "slope": 127, "yds": [416, 366, 512, 188, 567, 194, 302, 402, 446, 495, 186, 308, 161, 611, 464, 205, 378, 485]}, {"id": "nblue", "name": "Blue", "rating": 70.2, "slope": 124, "yds": [393, 346, 463, 162, 517, 160, 267, 388, 410, 473, 164, 288, 138, 578, 426, 185, 345, 445]}, {"id": "nwhite", "name": "White", "rating": 68, "slope": 121, "yds": [385, 326, 433, 152, 490, 158, 257, 359, 356, 436, 148, 268, 123, 552, 396, 175, 319, 424]}, {"id": "ngreen", "name": "Green", "rating": 65.7, "slope": 112, "yds": [361, 286, 405, 130, 475, 115, 228, 336, 313, 412, 123, 247, 95, 525, 382, 153, 299, 358]}, {"id": "nred", "name": "Red", "rating": 62.9, "slope": 108, "yds": [318, 206, 303, 115, 442, 105, 177, 289, 277, 387, 110, 217, 82, 503, 338, 110, 279, 340]}, {"id": "nblackw", "name": "Black (W)", "rating": 78.6, "slope": 141, "yds": [416, 366, 512, 188, 567, 194, 302, 402, 446, 495, 186, 308, 161, 611, 464, 205, 378, 485]}, {"id": "nbluew", "name": "Blue (W)", "rating": 75.6, "slope": 135, "yds": [393, 346, 463, 162, 517, 160, 267, 388, 410, 473, 164, 288, 138, 578, 426, 185, 345, 445]}, {"id": "nwhitew", "name": "White (W)", "rating": 73.5, "slope": 130, "yds": [385, 326, 433, 152, 490, 158, 257, 359, 356, 436, 148, 268, 123, 552, 396, 175, 319, 424]}, {"id": "ngreenw", "name": "Green (W)", "rating": 70.7, "slope": 122, "yds": [361, 286, 405, 130, 475, 115, 228, 336, 313, 412, 123, 247, 95, 525, 382, 153, 299, 358]}, {"id": "nredw", "name": "Red (W)", "rating": 66.5, "slope": 113, "yds": [318, 206, 303, 115, 442, 105, 177, 289, 277, 387, 110, 217, 82, 503, 338, 110, 279, 340]}], "holes": [{"par": 4, "si": 5}, {"par": 4, "si": 9}, {"par": 5, "si": 1}, {"par": 3, "si": 15}, {"par": 5, "si": 3}, {"par": 3, "si": 17}, {"par": 4, "si": 13}, {"par": 4, "si": 7}, {"par": 4, "si": 11}, {"par": 5, "si": 4}, {"par": 3, "si": 18}, {"par": 4, "si": 12}, {"par": 3, "si": 14}, {"par": 5, "si": 2}, {"par": 4, "si": 8}, {"par": 3, "si": 16}, {"par": 4, "si": 10}, {"par": 4, "si": 6}], "tier": "gps", "geoUrl": "geo/nat/tx/6619.json", "nVerified": 18, "solved": false}