{"id": "nat6983", "name": "Indian Springs Metropark Golf Course", "loc": [42.69778, -83.48931], "state": "Michigan", "teeSets": [{"id": "nblue", "name": "BLUE", "rating": 72.3, "slope": 123, "yds": [354, 408, 442, 186, 335, 425, 375, 189, 539, 406, 399, 169, 602, 398, 402, 129, 481, 449]}, {"id": "nwhite", "name": "WHITE", "rating": 71.3, "slope": 121, "yds": [342, 392, 427, 177, 319, 407, 368, 179, 526, 390, 389, 163, 586, 390, 386, 123, 471, 439]}, {"id": "nwhitegol", "name": "WHITE/GOLD", "rating": 68.9, "slope": 117, "yds": [342, 322, 317, 135, 319, 348, 368, 140, 526, 325, 389, 158, 586, 358, 386, 117, 471, 401]}, {"id": "ngold", "name": "GOLD", "rating": 66.5, "slope": 112, "yds": [294, 322, 317, 135, 235, 348, 340, 140, 440, 325, 378, 158, 502, 358, 320, 117, 429, 401]}, {"id": "nwhitew", "name": "WHITE (W)", "rating": 77.7, "slope": 134, "yds": [342, 392, 427, 177, 319, 407, 368, 179, 526, 390, 389, 163, 586, 390, 386, 123, 471, 439]}, {"id": "nwhitegolw", "name": "WHITE/GOLD (W)", "rating": 74.8, "slope": 130, "yds": [342, 322, 317, 135, 319, 348, 368, 140, 526, 325, 389, 158, 586, 358, 386, 117, 471, 401]}, {"id": "ngoldw", "name": "GOLD (W)", "rating": 72.1, "slope": 125, "yds": [294, 322, 317, 135, 235, 348, 340, 140, 440, 325, 378, 158, 502, 358, 320, 117, 429, 401]}, {"id": "ngreenw", "name": "GREEN (W)", "rating": 71.6, "slope": 121, "yds": [291, 319, 314, 132, 232, 345, 337, 137, 437, 322, 378, 158, 410, 355, 317, 117, 426, 398]}], "holes": [{"par": 4, "si": 11}, {"par": 4, "si": 7}, {"par": 4, "si": 1}, {"par": 3, "si": 15}, {"par": 4, "si": 17}, {"par": 4, "si": 3}, {"par": 4, "si": 9}, {"par": 3, "si": 13}, {"par": 5, "si": 5}, {"par": 4, "si": 8}, {"par": 4, "si": 12}, {"par": 3, "si": 16}, {"par": 5, "si": 2}, {"par": 4, "si": 14}, {"par": 4, "si": 10}, {"par": 3, "si": 18}, {"par": 5, "si": 4}, {"par": 4, "si": 6}], "tier": "gps", "geoUrl": "geo/nat/mi/6983.json", "nVerified": 18, "solved": false}