{"id": "nat7125", "name": "Wine Valley Golf Club", "loc": [46.05923, -118.50207], "state": "Washington", "teeSets": [{"id": "ngold", "name": "Gold", "rating": 76.2, "slope": 135, "yds": [460, 390, 574, 391, 505, 209, 624, 225, 476, 612, 180, 437, 512, 159, 518, 194, 459, 585]}, {"id": "ncabernet", "name": "Cabernet", "rating": 74.1, "slope": 131, "yds": [401, 390, 574, 391, 455, 180, 624, 202, 427, 581, 180, 406, 512, 159, 518, 176, 399, 585]}, {"id": "nblack", "name": "Black", "rating": 71.9, "slope": 128, "yds": [401, 359, 536, 351, 455, 180, 534, 202, 427, 581, 163, 406, 442, 135, 474, 176, 399, 550]}, {"id": "nmerlot", "name": "Merlot", "rating": 70.6, "slope": 128, "yds": [376, 359, 536, 351, 430, 165, 534, 182, 404, 528, 163, 381, 442, 135, 474, 155, 361, 550]}, {"id": "nblue", "name": "Blue", "rating": 70.1, "slope": 124, "yds": [376, 345, 508, 332, 430, 165, 509, 182, 404, 528, 151, 381, 420, 125, 463, 155, 361, 524]}, {"id": "nsyrah", "name": "Syrah", "rating": 68.8, "slope": 122, "yds": [350, 345, 508, 332, 390, 141, 509, 171, 388, 488, 151, 381, 383, 125, 432, 155, 334, 524]}, {"id": "nwhite", "name": "White", "rating": 67.8, "slope": 116, "yds": [350, 313, 476, 297, 390, 141, 488, 171, 388, 488, 124, 350, 383, 100, 432, 153, 334, 477]}, {"id": "nchardonn", "name": "Chardonnay", "rating": 65.8, "slope": 112, "yds": [330, 313, 430, 297, 294, 141, 439, 171, 341, 488, 96, 350, 358, 100, 380, 153, 299, 477]}, {"id": "nred", "name": "Red", "rating": 64.3, "slope": 109, "yds": [330, 229, 430, 262, 294, 101, 439, 146, 341, 434, 96, 325, 358, 84, 380, 126, 299, 438]}, {"id": "ngoldw", "name": "Gold (W)", "rating": 82.7, "slope": 150, "yds": [460, 390, 574, 391, 505, 209, 624, 225, 476, 612, 180, 437, 512, 159, 518, 194, 459, 585]}], "holes": [{"par": 4, "si": 7}, {"par": 4, "si": 11}, {"par": 5, "si": 3}, {"par": 4, "si": 15}, {"par": 4, "si": 1}, {"par": 3, "si": 17}, {"par": 5, "si": 9}, {"par": 3, "si": 13}, {"par": 4, "si": 5}, {"par": 5, "si": 6}, {"par": 3, "si": 16}, {"par": 4, "si": 4}, {"par": 4, "si": 2}, {"par": 3, "si": 18}, {"par": 5, "si": 12}, {"par": 3, "si": 14}, {"par": 4, "si": 8}, {"par": 5, "si": 10}], "tier": "gps", "geoUrl": "geo/nat/washington/7125.json", "nVerified": 18, "solved": false}