{"id": "nat7377", "name": "Pine Knolls Country Club", "loc": [41.30832, -93.08551], "state": "Iowa", "teeSets": [{"id": "nblue", "name": "Blue", "rating": 68.4, "slope": 124, "yds": [388, 231, 491, 434, 174, 332, 145, 381, 337, 388, 231, 491, 434, 174, 332, 145, 381, 337]}, {"id": "nbluewhit", "name": "Blue/White", "rating": 67.3, "slope": 123, "yds": [388, 231, 491, 434, 174, 332, 145, 381, 337, 375, 200, 480, 415, 155, 317, 130, 321, 301]}, {"id": "nwhite", "name": "White", "rating": 66.2, "slope": 122, "yds": [375, 200, 480, 415, 155, 317, 130, 321, 301, 375, 200, 480, 415, 155, 317, 130, 321, 301]}, {"id": "ngold", "name": "Gold", "rating": 62.6, "slope": 108, "yds": [365, 145, 400, 300, 145, 270, 110, 295, 267, 365, 145, 400, 300, 145, 270, 110, 295, 267]}, {"id": "nred", "name": "Red", "rating": 62.2, "slope": 101, "yds": [305, 160, 400, 300, 140, 270, 114, 291, 237, 305, 160, 400, 300, 140, 270, 114, 291, 237]}, {"id": "nbluew", "name": "Blue (W)", "rating": 74.8, "slope": 131, "yds": [388, 231, 491, 434, 174, 332, 145, 381, 337, 388, 231, 491, 434, 174, 332, 145, 381, 337]}, {"id": "nbluewhitw", "name": "Blue/White (W)", "rating": 73.5, "slope": 127, "yds": [388, 231, 491, 434, 174, 332, 145, 381, 337, 375, 200, 480, 415, 155, 317, 130, 321, 301]}, {"id": "nwhitew", "name": "White (W)", "rating": 72.2, "slope": 123, "yds": [375, 200, 480, 415, 155, 317, 130, 321, 301, 375, 200, 480, 415, 155, 317, 130, 321, 301]}, {"id": "ngoldw", "name": "Gold (W)", "rating": 67, "slope": 116, "yds": [365, 145, 400, 300, 145, 270, 110, 295, 267, 365, 145, 400, 300, 145, 270, 110, 295, 267]}, {"id": "nredw", "name": "Red (W)", "rating": 66.4, "slope": 114, "yds": [305, 160, 400, 300, 145, 270, 110, 295, 231, 305, 160, 400, 300, 145, 270, 110, 295, 231]}], "holes": [{"par": 4, "si": 3}, {"par": 3, "si": 9}, {"par": 5, "si": 15}, {"par": 5, "si": 17}, {"par": 3, "si": 13}, {"par": 4, "si": 5}, {"par": 3, "si": 1}, {"par": 4, "si": 7}, {"par": 4, "si": 11}], "tier": "greens", "geoUrl": "geo/nat/iowa/g7377.json", "nGreens": 11}