{"id": "nat7969", "name": "Country Club of Canton", "loc": [32.60916, -89.99137], "state": "Mississippi", "teeSets": [{"id": "nblue", "name": "Blue", "rating": 69.3, "slope": 120, "yds": [392, 341, 184, 494, 469, 197, 555, 402, 212, 313, 535, 145, 394, 377, 270, 342, 171, 513]}, {"id": "nwhite", "name": "White", "rating": 66.6, "slope": 117, "yds": [383, 322, 154, 476, 453, 192, 511, 340, 196, 304, 516, 120, 381, 359, 255, 327, 139, 472]}, {"id": "ngold", "name": "Gold", "rating": 63.9, "slope": 106, "yds": [298, 272, 147, 388, 422, 154, 474, 271, 158, 216, 450, 109, 336, 319, 214, 291, 117, 461]}, {"id": "nredw", "name": "Red (W)", "rating": 67.4, "slope": 112, "yds": [298, 272, 140, 384, 397, 151, 470, 267, 145, 213, 440, 90, 324, 315, 207, 286, 106, 437]}], "holes": [{"par": 4, "si": 4}, {"par": 4, "si": 12}, {"par": 3, "si": 16}, {"par": 5, "si": 10}, {"par": 5, "si": 18}, {"par": 3, "si": 6}, {"par": 5, "si": 2}, {"par": 4, "si": 14}, {"par": 3, "si": 8}, {"par": 4, "si": 13}, {"par": 5, "si": 1}, {"par": 3, "si": 15}, {"par": 4, "si": 5}, {"par": 4, "si": 3}, {"par": 4, "si": 11}, {"par": 4, "si": 7}, {"par": 3, "si": 17}, {"par": 5, "si": 9}], "tier": "gps", "geoUrl": "geo/nat/mississippi/7969.json", "nVerified": 16, "solved": false}