{"id": "nat7467", "name": "Arcadian Shores Golf Club", "loc": [33.77961, -78.7792], "state": "South Carolina", "teeSets": [{"id": "nblack", "name": "Black", "rating": 73.1, "slope": 146, "yds": [520, 197, 504, 397, 400, 411, 358, 168, 372, 500, 425, 380, 406, 392, 207, 557, 164, 423]}, {"id": "nblue", "name": "Blue", "rating": 71.6, "slope": 140, "yds": [500, 174, 468, 384, 385, 387, 351, 138, 351, 468, 391, 368, 383, 382, 187, 533, 156, 399]}, {"id": "nwhite", "name": "White", "rating": 69.3, "slope": 135, "yds": [484, 148, 463, 370, 370, 373, 332, 148, 331, 441, 357, 355, 367, 271, 168, 509, 138, 363]}, {"id": "ngold", "name": "Gold", "rating": 67.6, "slope": 126, "yds": [458, 143, 423, 355, 348, 359, 309, 129, 293, 430, 311, 341, 349, 264, 147, 489, 115, 342]}, {"id": "nred", "name": "Red", "rating": 65.3, "slope": 117, "yds": [407, 114, 413, 339, 329, 323, 296, 103, 283, 397, 276, 306, 274, 254, 112, 454, 91, 305]}, {"id": "nwhitew", "name": "White (W)", "rating": 75.2, "slope": 140, "yds": [484, 148, 463, 370, 370, 373, 332, 148, 331, 441, 357, 355, 367, 271, 168, 509, 138, 363]}, {"id": "ngoldw", "name": "Gold (W)", "rating": 72.9, "slope": 132, "yds": [458, 143, 423, 355, 348, 359, 309, 129, 293, 430, 311, 341, 349, 264, 147, 489, 115, 342]}, {"id": "nredw", "name": "Red (W)", "rating": 69.9, "slope": 125, "yds": [407, 114, 413, 339, 329, 323, 296, 103, 283, 397, 276, 306, 274, 254, 112, 454, 91, 305]}], "holes": [{"par": 5, "si": 8}, {"par": 3, "si": 4}, {"par": 5, "si": 10}, {"par": 4, "si": 12}, {"par": 4, "si": 2}, {"par": 4, "si": 6}, {"par": 4, "si": 18}, {"par": 3, "si": 16}, {"par": 4, "si": 14}, {"par": 5, "si": 9}, {"par": 4, "si": 3}, {"par": 4, "si": 13}, {"par": 4, "si": 1}, {"par": 4, "si": 11}, {"par": 3, "si": 15}, {"par": 5, "si": 7}, {"par": 3, "si": 17}, {"par": 4, "si": 5}], "tier": "gps", "geoUrl": "geo/nat/southcarolin/7467.json", "nVerified": 17, "solved": false}