{"id": "nat8829", "name": "Centennial Valley", "loc": [35.10476, -92.50217], "state": "Arkansas", "teeSets": [{"id": "nblack", "name": "Black", "rating": 74.1, "slope": 126, "yds": [394, 200, 364, 203, 433, 425, 540, 409, 534, 493, 397, 456, 376, 190, 557, 206, 400, 380]}, {"id": "nblue", "name": "Blue", "rating": 71.4, "slope": 118, "yds": [373, 179, 344, 181, 396, 365, 450, 371, 490, 474, 379, 430, 344, 175, 515, 190, 355, 355]}, {"id": "nwhite", "name": "White", "rating": 67.2, "slope": 109, "yds": [339, 145, 322, 120, 350, 343, 430, 325, 412, 430, 305, 396, 266, 162, 481, 125, 310, 339]}, {"id": "ngold", "name": "Gold", "rating": 64.3, "slope": 102, "yds": [310, 117, 265, 105, 306, 326, 394, 273, 377, 412, 295, 337, 244, 126, 457, 123, 264, 276]}, {"id": "nwhitew", "name": "White (W)", "rating": 74.2, "slope": 126, "yds": [339, 160, 322, 154, 364, 362, 471, 350, 484, 430, 359, 396, 292, 162, 511, 170, 356, 339]}, {"id": "ngoldw", "name": "Gold (W)", "rating": 70.8, "slope": 124, "yds": [310, 117, 265, 105, 306, 326, 394, 273, 378, 412, 275, 337, 244, 126, 457, 123, 265, 276]}, {"id": "nredw", "name": "Red (W)", "rating": 65.1, "slope": 113, "yds": [272, 110, 231, 98, 273, 303, 336, 248, 348, 372, 294, 312, 220, 98, 398, 100, 226, 223]}], "holes": [{"par": 4, "si": 7}, {"par": 3, "si": 3}, {"par": 4, "si": 17}, {"par": 3, "si": 9}, {"par": 4, "si": 5}, {"par": 4, "si": 1}, {"par": 5, "si": 11}, {"par": 4, "si": 13}, {"par": 5, "si": 15}, {"par": 5, "si": 18}, {"par": 4, "si": 2}, {"par": 4, "si": 4}, {"par": 4, "si": 14}, {"par": 3, "si": 8}, {"par": 5, "si": 16}, {"par": 3, "si": 6}, {"par": 4, "si": 10}, {"par": 4, "si": 12}], "tier": "gps", "geoUrl": "geo/nat/arkansas/8829.json", "nVerified": 12, "solved": false}