{"id": "nat8911", "name": "Mission Valley Golf & Country Club", "loc": [27.15926, -82.44904], "state": "Florida", "teeSets": [{"id": "n6", "name": "#6", "rating": 72.2, "slope": 131, "yds": [377, 198, 561, 419, 381, 341, 343, 219, 501, 388, 184, 333, 506, 362, 188, 435, 486, 432]}, {"id": "n5", "name": "#5", "rating": 71.1, "slope": 128, "yds": [371, 184, 549, 383, 376, 311, 330, 211, 482, 379, 173, 319, 493, 354, 166, 426, 476, 413]}, {"id": "n45combo", "name": "#4 / #5 COMBO", "rating": 69.6, "slope": 126, "yds": [371, 184, 475, 352, 347, 311, 330, 211, 482, 379, 173, 319, 456, 354, 166, 373, 476, 340]}, {"id": "n4", "name": "#4", "rating": 67.6, "slope": 118, "yds": [331, 166, 475, 352, 347, 273, 312, 168, 450, 318, 145, 284, 456, 317, 141, 373, 426, 340]}, {"id": "n34combo", "name": "#3 / #4 COMBO", "rating": 66.6, "slope": 115, "yds": [331, 166, 456, 338, 320, 273, 312, 168, 450, 318, 145, 284, 388, 317, 141, 347, 426, 315]}, {"id": "n3", "name": "#3", "rating": 65.1, "slope": 113, "yds": [294, 150, 456, 338, 320, 246, 294, 136, 414, 313, 114, 255, 388, 307, 129, 347, 395, 315]}, {"id": "n23combo", "name": "#2 / #3 COMBO", "rating": 63.9, "slope": 110, "yds": [294, 150, 402, 256, 277, 246, 294, 136, 414, 313, 114, 255, 377, 268, 129, 307, 395, 315]}, {"id": "n2", "name": "#2", "rating": 62.6, "slope": 109, "yds": [251, 127, 402, 256, 277, 241, 265, 114, 363, 310, 109, 237, 377, 268, 122, 307, 346, 300]}, {"id": "n1", "name": "#1", "rating": 61.1, "slope": 105, "yds": [236, 121, 377, 249, 237, 211, 253, 102, 357, 253, 103, 210, 364, 244, 94, 292, 294, 255]}, {"id": "n4w", "name": "#4 (W)", "rating": 72.8, "slope": 132, "yds": [331, 166, 475, 352, 347, 273, 312, 168, 450, 318, 145, 284, 456, 317, 141, 373, 426, 340]}], "holes": [{"par": 4, "si": 7}, {"par": 3, "si": 15}, {"par": 5, "si": 1}, {"par": 4, "si": 5}, {"par": 4, "si": 3}, {"par": 4, "si": 17}, {"par": 4, "si": 11}, {"par": 3, "si": 13}, {"par": 5, "si": 9}, {"par": 4, "si": 6}, {"par": 3, "si": 16}, {"par": 4, "si": 14}, {"par": 5, "si": 4}, {"par": 4, "si": 8}, {"par": 3, "si": 18}, {"par": 4, "si": 2}, {"par": 5, "si": 12}, {"par": 4, "si": 10}], "tier": "gps", "geoUrl": "geo/nat/fl/8911.json", "nVerified": 15, "solved": false}