{"id": "nat9131", "name": "Farmington Country Club", "loc": [38.06082, -78.53906], "state": "Virginia", "teeSets": [{"id": "ncoorecre", "name": "Coore Crenshaw", "rating": 30.8, "slope": 111, "yds": [190, 252, 148, 364, 374, 165, 147, 124, 407]}, {"id": "nthree", "name": "Three", "rating": 30.2, "slope": 108, "yds": [168, 252, 148, 327, 350, 165, 133, 124, 359]}, {"id": "ntwo", "name": "Two", "rating": 29.6, "slope": 103, "yds": [146, 228, 124, 300, 330, 155, 109, 100, 341]}, {"id": "none", "name": "One", "rating": 28.6, "slope": 99, "yds": [119, 206, 92, 246, 292, 119, 88, 66, 321]}, {"id": "ncoorecrew", "name": "Coore Crenshaw (W)", "rating": 32.7, "slope": 114, "yds": [190, 252, 148, 364, 374, 165, 147, 124, 407]}, {"id": "nthreew", "name": "Three (W)", "rating": 31.8, "slope": 113, "yds": [168, 252, 148, 327, 350, 165, 133, 124, 359]}, {"id": "ntwow", "name": "Two (W)", "rating": 30.6, "slope": 109, "yds": [146, 228, 124, 300, 330, 155, 109, 100, 341]}, {"id": "nonew", "name": "One (W)", "rating": 29.7, "slope": 103, "yds": [119, 206, 92, 246, 292, 119, 88, 66, 321]}], "holes": [{"par": 3, "si": 6}, {"par": 4, "si": 4}, {"par": 3, "si": 7}, {"par": 4, "si": 1}, {"par": 4, "si": 3}, {"par": 3, "si": 5}, {"par": 3, "si": 8}, {"par": 3, "si": 9}, {"par": 5, "si": 2}], "tier": "greens", "geoUrl": "geo/nat/virginia/g9131.json", "nGreens": 13}