{"id": "nat9684", "name": "Clear Lake Public GC", "loc": [44.74871, -96.68916], "state": "South Dakota", "teeSets": [{"id": "nwhite", "name": "WHITE", "rating": 67.4, "slope": 123, "yds": [402, 376, 188, 161, 408, 147, 381, 341, 371, 402, 376, 188, 161, 408, 147, 381, 341, 371]}, {"id": "ngold", "name": "GOLD", "rating": 63, "slope": 113, "yds": [342, 330, 147, 157, 318, 131, 310, 302, 318, 342, 330, 147, 157, 318, 131, 310, 302, 318]}, {"id": "nwhitew", "name": "WHITE (W)", "rating": 72.4, "slope": 127, "yds": [402, 376, 188, 161, 408, 147, 381, 341, 371, 402, 376, 188, 161, 408, 147, 381, 341, 371]}, {"id": "ngoldw", "name": "GOLD (W)", "rating": 67.6, "slope": 118, "yds": [342, 330, 147, 157, 318, 131, 310, 302, 318, 342, 330, 147, 157, 318, 131, 310, 302, 318]}, {"id": "nredw", "name": "RED (W)", "rating": 67, "slope": 116, "yds": [340, 326, 143, 153, 291, 115, 306, 298, 314, 340, 326, 143, 153, 291, 115, 306, 298, 314]}], "holes": [{"par": 4, "si": 5}, {"par": 4, "si": 7}, {"par": 3, "si": 13}, {"par": 3, "si": 17}, {"par": 4, "si": 1}, {"par": 3, "si": 15}, {"par": 4, "si": 3}, {"par": 4, "si": 11}, {"par": 4, "si": 9}], "tier": "gps", "geoUrl": "geo/nat/southdakota/9684.json", "nVerified": 9, "solved": false}